{
  "format_version": "1",
  "execution_id": "fc0d865b-485e-48b4-8d19-f8f8e312667a",
  "workflow_hash": "008e8469cd7b4222c24cbe0b5d5087d578aa10f0b82cf6fd2837704e9581d558",
  "created_at": "2026-05-26T16:58:08.827027818Z",
  "ready_queue": [
    "slow_task"
  ],
  "context": {},
  "trigger_payload": {},
  "task_iterations": {
    "quick_exit": 1,
    "start": 1
  },
  "total_iterations": 2,
  "completed": {
    "start": {
      "task_id": "start",
      "run_seq": 1,
      "started_at": "2026-05-26T16:58:08.825576054Z",
      "completed_at": "2026-05-26T16:58:08.825584109Z",
      "status": "success",
      "output_ref": {
        "type": "inline",
        "value": {
          "status": "ok"
        }
      },
      "error": null,
      "resolved_params_snapshot": {}
    },
    "quick_exit": {
      "task_id": "quick_exit",
      "run_seq": 1,
      "started_at": "2026-05-26T16:58:08.826391081Z",
      "completed_at": "2026-05-26T16:58:08.826398825Z",
      "status": "success",
      "output_ref": {
        "type": "inline",
        "value": {
          "status": "ok"
        }
      },
      "error": null,
      "resolved_params_snapshot": {}
    }
  },
  "version": 2,
  "runtime_tasks": [
    {
      "id": "start",
      "operator": "NoOpOperator",
      "params": {},
      "name": null,
      "classes": [],
      "timeout_ms": null,
      "retry": null,
      "max_iterations": null,
      "parallel_group": null,
      "transitions": [
        {
          "to": "quick_exit",
          "when": null,
          "priority": 100,
          "label": null
        },
        {
          "to": "slow_task",
          "when": null,
          "priority": 100,
          "label": null
        }
      ],
      "goal_gate": false
    },
    {
      "id": "slow_task",
      "operator": "NoOpOperator",
      "params": {},
      "name": null,
      "classes": [],
      "timeout_ms": null,
      "retry": null,
      "max_iterations": null,
      "parallel_group": null,
      "transitions": [],
      "goal_gate": false
    },
    {
      "id": "quick_exit",
      "operator": "NoOpOperator",
      "params": {},
      "name": null,
      "classes": [],
      "timeout_ms": null,
      "retry": null,
      "max_iterations": null,
      "parallel_group": null,
      "transitions": [],
      "goal_gate": false,
      "terminal": "success"
    }
  ],
  "io_snapshot": {}
}