{
  "format_version": "1",
  "execution_id": "53160169-b55e-4da9-9b4b-0bade359a4a7",
  "workflow_hash": "994e62a86e9b03c5e16ac1b5836fd60dce7e20af819a96631ac4cb7585f61218",
  "created_at": "2026-05-22T05:19:41.676398499Z",
  "ready_queue": [],
  "context": {},
  "trigger_payload": {},
  "task_iterations": {
    "will_fail": 1,
    "start": 1
  },
  "total_iterations": 2,
  "completed": {
    "will_fail": {
      "task_id": "will_fail",
      "run_seq": 1,
      "started_at": "2026-05-22T05:19:41.676342144Z",
      "completed_at": "2026-05-22T05:19:41.676347444Z",
      "status": "failed",
      "output_ref": {
        "type": "inline",
        "value": "intentional failure from FailOperator"
      },
      "error": {
        "code": "ERR-db54b6bb-af57-4fb9-80f3-a6367b5f0e23",
        "category": "ValidationError",
        "message": "intentional failure from FailOperator"
      },
      "resolved_params_snapshot": {}
    },
    "start": {
      "task_id": "start",
      "run_seq": 1,
      "started_at": "2026-05-22T05:19:41.676063355Z",
      "completed_at": "2026-05-22T05:19:41.676066701Z",
      "status": "success",
      "output_ref": {
        "type": "inline",
        "value": {
          "status": "ok"
        }
      },
      "error": null,
      "resolved_params_snapshot": {}
    }
  },
  "version": 2,
  "runtime_tasks": [
    {
      "id": "will_fail",
      "operator": "FailOperator",
      "params": {},
      "name": null,
      "classes": [],
      "timeout_ms": null,
      "retry": null,
      "max_iterations": null,
      "parallel_group": null,
      "transitions": [],
      "goal_gate": false
    },
    {
      "id": "never_runs",
      "operator": "NoOpOperator",
      "params": {},
      "name": null,
      "classes": [],
      "timeout_ms": null,
      "retry": null,
      "max_iterations": null,
      "parallel_group": null,
      "transitions": [],
      "goal_gate": false
    },
    {
      "id": "start",
      "operator": "NoOpOperator",
      "params": {},
      "name": null,
      "classes": [],
      "timeout_ms": null,
      "retry": null,
      "max_iterations": null,
      "parallel_group": null,
      "transitions": [
        {
          "to": "will_fail",
          "when": null,
          "priority": 100,
          "label": null
        }
      ],
      "goal_gate": false
    }
  ],
  "io_snapshot": {}
}