{
  "format_version": "1",
  "execution_id": "2f2e063c-ece4-4ed8-a8cc-abf3e44af05f",
  "workflow_hash": "8a255122395250eaf585d4d3892e57854953983de2b6bc5caf52ea5131464beb",
  "created_at": "2026-05-26T18:41:26.573238203Z",
  "ready_queue": [],
  "context": {},
  "trigger_payload": {},
  "task_iterations": {
    "start": 1,
    "gate": 1
  },
  "total_iterations": 2,
  "completed": {
    "gate": {
      "task_id": "gate",
      "run_seq": 1,
      "started_at": "2026-05-26T18:41:26.572056680Z",
      "completed_at": "2026-05-26T18:41:26.572063292Z",
      "status": "failed",
      "output_ref": {
        "type": "inline",
        "value": "intentional failure from FailOperator"
      },
      "error": {
        "code": "ERR-00d4fce0-f735-4bb2-8468-e54568624988",
        "category": "ValidationError",
        "message": "intentional failure from FailOperator"
      },
      "resolved_params_snapshot": {}
    },
    "start": {
      "task_id": "start",
      "run_seq": 1,
      "started_at": "2026-05-26T18:41:26.571734364Z",
      "completed_at": "2026-05-26T18:41:26.571738862Z",
      "status": "success",
      "output_ref": {
        "type": "inline",
        "value": {
          "status": "ok"
        }
      },
      "error": null,
      "resolved_params_snapshot": {}
    }
  },
  "version": 2,
  "runtime_tasks": [
    {
      "id": "gate",
      "operator": "FailOperator",
      "params": {},
      "name": null,
      "classes": [],
      "timeout_ms": null,
      "retry": null,
      "max_iterations": null,
      "parallel_group": null,
      "transitions": [],
      "goal_gate": true
    },
    {
      "id": "start",
      "operator": "NoOpOperator",
      "params": {},
      "name": null,
      "classes": [],
      "timeout_ms": null,
      "retry": null,
      "max_iterations": null,
      "parallel_group": null,
      "transitions": [
        {
          "to": "gate",
          "when": null,
          "priority": 100,
          "label": null
        }
      ],
      "goal_gate": false
    }
  ],
  "io_snapshot": {}
}