{
  "format_version": "1",
  "execution_id": "e3a572c1-d828-460f-80b9-f16a8bfe9f08",
  "workflow_hash": "323b9b3b425ee24d102707d196708a3a35680477a598d8d52a5660e2f60e48b3",
  "created_at": "2026-05-14T12:35:37.510464115Z",
  "ready_queue": [],
  "context": {},
  "trigger_payload": {},
  "task_iterations": {
    "done": 1,
    "branch_a": 1,
    "start": 1
  },
  "total_iterations": 3,
  "completed": {
    "start": {
      "task_id": "start",
      "run_seq": 1,
      "started_at": "2026-05-14T12:35:37.504748333Z",
      "completed_at": "2026-05-14T12:35:37.504753422Z",
      "status": "success",
      "output_ref": {
        "type": "inline",
        "value": {
          "status": "ok"
        }
      },
      "error": null,
      "resolved_params_snapshot": {}
    },
    "branch_a": {
      "task_id": "branch_a",
      "run_seq": 1,
      "started_at": "2026-05-14T12:35:37.505170996Z",
      "completed_at": "2026-05-14T12:35:37.505175053Z",
      "status": "success",
      "output_ref": {
        "type": "inline",
        "value": {
          "status": "ok"
        }
      },
      "error": null,
      "resolved_params_snapshot": {}
    },
    "done": {
      "task_id": "done",
      "run_seq": 1,
      "started_at": "2026-05-14T12:35:37.509529562Z",
      "completed_at": "2026-05-14T12:35:37.509540783Z",
      "status": "success",
      "output_ref": {
        "type": "inline",
        "value": {
          "status": "ok"
        }
      },
      "error": null,
      "resolved_params_snapshot": {}
    }
  },
  "version": 2,
  "runtime_tasks": [
    {
      "id": "branch_b",
      "operator": "NoOpOperator",
      "params": {},
      "name": null,
      "classes": [],
      "timeout_ms": null,
      "retry": null,
      "max_iterations": null,
      "parallel_group": null,
      "transitions": [
        {
          "to": "done",
          "when": {
            "$expr": "true"
          },
          "priority": 100,
          "label": null
        }
      ],
      "goal_gate": false
    },
    {
      "id": "start",
      "operator": "NoOpOperator",
      "params": {},
      "name": null,
      "classes": [],
      "timeout_ms": null,
      "retry": null,
      "max_iterations": null,
      "parallel_group": null,
      "transitions": [
        {
          "to": "branch_a",
          "when": {
            "$expr": "true"
          },
          "priority": 100,
          "label": null
        },
        {
          "to": "branch_b",
          "when": {
            "$expr": "true"
          },
          "priority": 100,
          "label": null
        }
      ],
      "goal_gate": false
    },
    {
      "id": "done",
      "operator": "NoOpOperator",
      "params": {},
      "name": null,
      "classes": [],
      "timeout_ms": null,
      "retry": null,
      "max_iterations": null,
      "parallel_group": null,
      "transitions": [],
      "goal_gate": false
    },
    {
      "id": "branch_a",
      "operator": "NoOpOperator",
      "params": {},
      "name": null,
      "classes": [],
      "timeout_ms": null,
      "retry": null,
      "max_iterations": null,
      "parallel_group": null,
      "transitions": [
        {
          "to": "done",
          "when": {
            "$expr": "true"
          },
          "priority": 100,
          "label": null
        }
      ],
      "goal_gate": false
    }
  ],
  "io_snapshot": {}
}