{
  "format_version": "1",
  "execution_id": "3d81bf12-b081-4859-8e2e-319f49c83e41",
  "workflow_hash": "43da731e6838e8b13fe7a7646b8aae9f6635d8d77c54c887974e6dabaeef214b",
  "created_at": "2026-05-09T16:43:13.838251990Z",
  "ready_queue": [],
  "context": {},
  "trigger_payload": {},
  "task_iterations": {
    "done": 1,
    "start": 1,
    "security_scan": 1
  },
  "total_iterations": 3,
  "completed": {
    "done": {
      "task_id": "done",
      "run_seq": 1,
      "started_at": "2026-05-09T16:43:13.837897805Z",
      "completed_at": "2026-05-09T16:43:13.837903505Z",
      "status": "success",
      "output_ref": {
        "type": "inline",
        "value": {
          "status": "ok"
        }
      },
      "error": null,
      "resolved_params_snapshot": {}
    },
    "start": {
      "task_id": "start",
      "run_seq": 1,
      "started_at": "2026-05-09T16:43:13.808659933Z",
      "completed_at": "2026-05-09T16:43:13.808667126Z",
      "status": "success",
      "output_ref": {
        "type": "inline",
        "value": {
          "status": "ok"
        }
      },
      "error": null,
      "resolved_params_snapshot": {}
    },
    "security_scan": {
      "task_id": "security_scan",
      "run_seq": 1,
      "started_at": "2026-05-09T16:43:13.836488038Z",
      "completed_at": "2026-05-09T16:43:13.836495541Z",
      "status": "success",
      "output_ref": {
        "type": "inline",
        "value": {
          "status": "ok"
        }
      },
      "error": null,
      "resolved_params_snapshot": {}
    }
  },
  "version": 2,
  "runtime_tasks": [
    {
      "id": "security_scan",
      "operator": "NoOpOperator",
      "params": {},
      "name": null,
      "classes": [],
      "timeout_ms": null,
      "retry": null,
      "max_iterations": null,
      "parallel_group": null,
      "transitions": [
        {
          "to": "done",
          "when": null,
          "priority": 100,
          "label": null
        }
      ],
      "goal_gate": true
    },
    {
      "id": "done",
      "operator": "NoOpOperator",
      "params": {},
      "name": null,
      "classes": [],
      "timeout_ms": null,
      "retry": null,
      "max_iterations": null,
      "parallel_group": null,
      "transitions": [],
      "goal_gate": false,
      "terminal": "success"
    },
    {
      "id": "start",
      "operator": "NoOpOperator",
      "params": {},
      "name": null,
      "classes": [],
      "timeout_ms": null,
      "retry": null,
      "max_iterations": null,
      "parallel_group": null,
      "transitions": [
        {
          "to": "security_scan",
          "when": null,
          "priority": 100,
          "label": null
        }
      ],
      "goal_gate": false
    }
  ],
  "io_snapshot": {}
}